{
  "FILE NAME": "15_X000_C194_1111_4.jpg",
  "COLLECTION METHOD": "제작자료",
  "FORM": "이미지",
  "DATE": "2020-11-11 14:54:39",
  "GPS": "37.5213034166667/126.744009972222",
  "ID CODE": "C194",
  "RESOLUTION": "1920*1080",
  "focus distance": "3.60mm",
  "exposure time": "1/120sec",
  "Aperture values": "1.85",
  "Sensitivity iso": "64",
  "exposure method": "not defined",
  "MAKE": "samsung",
  "Camera Model Name": "SM-J415N",
  "Software": "J415NKOU2BTG6",
  "File Size": "368577",
  "DAY/NIGHT": "주간",
  "PLACE": "실외",
  "PROJECT SORTING": "생활폐기물",
  "BoundingCount": "1",
  "Bounding": [
    {
      "CLASS": "비닐류",
      "DETAILS": "포장제",
      "DAMAGE": "원형",
      "TRANSPARENCY": "투명",
      "Color": "129/147/158",
      "Shape": "다면체",
      "Texture": "딱딱함",
      "Object Size": "중",
      "Direction": "측면",
      "Drawing": "BOX",
      "x1": "139",
      "y1": "301",
      "x2": "1705",
      "y2": "708"
    }
  ]
}